cloudwatch_logs_environment/__init__.py
cloudwatch_logs_environment/confgen.py
cloudwatch_logs_environment/runner.py
cloudwatch_logs_environment/version.py
cloudwatch_logs_environment/test/__init__.py
cloudwatch_logs_environment/test/test_confgen.py
cloudwatch_logs_environment-1.0.0.dist-info/DESCRIPTION.rst
cloudwatch_logs_environment-1.0.0.dist-info/METADATA
cloudwatch_logs_environment-1.0.0.dist-info/RECORD
cloudwatch_logs_environment-1.0.0.dist-info/WHEEL
cloudwatch_logs_environment-1.0.0.dist-info/entry_points.txt
cloudwatch_logs_environment-1.0.0.dist-info/metadata.json
cloudwatch_logs_environment-1.0.0.dist-info/top_level.txt
