Metadata-Version: 2.0
Name: cloudwatch-logs-environment
Version: 1.0.0
Summary: CloudWatch logs configuration management via environment variables
Home-page: https://github.com/nickrw/cloudwatch_logs_environment
Author: Nicholas Robinson-Wall
Author-email: nick@robinson-wall.com
License: MIT
Platform: UNKNOWN
Classifier: Development Status :: 5 - Production/Stable
Classifier: License :: OSI Approved :: MIT License
Classifier: Programming Language :: Python :: 3 :: Only
Classifier: Intended Audience :: System Administrators
Classifier: Intended Audience :: Developers
Requires-Dist: awscli (==1.11.16)
Requires-Dist: awscli-cwlogs (==1.4.0)
